{
  "slug": "duquesne",
  "period": "2025-Q3",
  "period_ending": "2025-09-30",
  "filing_date": "2025-11-14",
  "accession": "0001536411-25-000017",
  "edgar_url": "https://www.sec.gov/Archives/edgar/data/1536411/000153641125000017/",
  "value_units": "USD_THOUSANDS",
  "schema_version": "X02",
  "total_value": 4062003000,
  "position_count": 65,
  "positions": [
    {
      "cusip": "00835Q202",
      "name_of_issuer": "Aeva Technologies Inc",
      "title_of_class": "COM NEW",
      "shares": 1839314,
      "shares_type": "SH",
      "value": 26670000,
      "put_call": null,
      "investment_discretion": "DFND",
      "voting_sole": 1839314,
      "voting_shared": 0,
      "voting_none": 0
    },
    {
      "cusip": "02079K305",
      "name_of_issuer": "Alphabet Inc",
      "title_of_class": "CAP STK CL A",
      "shares": 102200,
      "shares_type": "SH",
      "value": 24845000,
      "put_call": null,
      "investment_discretion": "DFND",
      "voting_sole": 102200,
      "voting_shared": 0,
      "voting_none": 0
    },
    {
      "cusip": "023135106",
      "name_of_issuer": "Amazon Com Inc",
      "title_of_class": "COM",
      "shares": 437070,
      "shares_type": "SH",
      "value": 95967000,
      "put_call": null,
      "investment_discretion": "DFND",
      "voting_sole": 437070,
      "voting_shared": 0,
      "voting_none": 0
    },
    {
      "cusip": "042068205",
      "name_of_issuer": "Arm Holdings Plc",
      "title_of_class": "SPONSORED ADS",
      "shares": 167900,
      "shares_type": "SH",
      "value": 23756000,
      "put_call": null,
      "investment_discretion": "DFND",
      "voting_sole": 167900,
      "voting_shared": 0,
      "voting_none": 0
    },
    {
      "cusip": "060505104",
      "name_of_issuer": "Bank America Corp",
      "title_of_class": "COM",
      "shares": 989250,
      "shares_type": "SH",
      "value": 51035000,
      "put_call": null,
      "investment_discretion": "DFND",
      "voting_sole": 989250,
      "voting_shared": 0,
      "voting_none": 0
    },
    {
      "cusip": "G0896C103",
      "name_of_issuer": "Bbb Foods Inc",
      "title_of_class": "CL A COM",
      "shares": 1183125,
      "shares_type": "SH",
      "value": 31897000,
      "put_call": null,
      "investment_discretion": "DFND",
      "voting_sole": 1183125,
      "voting_shared": 0,
      "voting_none": 0
    },
    {
      "cusip": "14040H105",
      "name_of_issuer": "Capital One Finl Corp",
      "title_of_class": "COM",
      "shares": 43920,
      "shares_type": "SH",
      "value": 9337000,
      "put_call": null,
      "investment_discretion": "DFND",
      "voting_sole": 43920,
      "voting_shared": 0,
      "voting_none": 0
    },
    {
      "cusip": "144285103",
      "name_of_issuer": "Carpenter Technology Corp",
      "title_of_class": "COM",
      "shares": 220035,
      "shares_type": "SH",
      "value": 54027000,
      "put_call": null,
      "investment_discretion": "DFND",
      "voting_sole": 220035,
      "voting_shared": 0,
      "voting_none": 0
    },
    {
      "cusip": "16935C109",
      "name_of_issuer": "Chime Finl Inc",
      "title_of_class": "COM SHS CL A",
      "shares": 43230,
      "shares_type": "SH",
      "value": 872000,
      "put_call": null,
      "investment_discretion": "DFND",
      "voting_sole": 43230,
      "voting_shared": 0,
      "voting_none": 0
    },
    {
      "cusip": "169656105",
      "name_of_issuer": "Chipotle Mexican Grill Inc",
      "title_of_class": "COM",
      "shares": 233205,
      "shares_type": "SH",
      "value": 9139000,
      "put_call": null,
      "investment_discretion": "DFND",
      "voting_sole": 233205,
      "voting_shared": 0,
      "voting_none": 0
    },
    {
      "cusip": "172967424",
      "name_of_issuer": "Citigroup Inc",
      "title_of_class": "COM NEW",
      "shares": 514850,
      "shares_type": "SH",
      "value": 52257000,
      "put_call": null,
      "investment_discretion": "DFND",
      "voting_sole": 514850,
      "voting_shared": 0,
      "voting_none": 0
    },
    {
      "cusip": "185899101",
      "name_of_issuer": "Cleveland-Cliffs Inc New",
      "title_of_class": "COM",
      "shares": 2715035,
      "shares_type": "SH",
      "value": 33123000,
      "put_call": null,
      "investment_discretion": "DFND",
      "voting_sole": 2715035,
      "voting_shared": 0,
      "voting_none": 0
    },
    {
      "cusip": "19240Q201",
      "name_of_issuer": "Cogent Biosciences Inc",
      "title_of_class": "COM",
      "shares": 1059580,
      "shares_type": "SH",
      "value": 15216000,
      "put_call": null,
      "investment_discretion": "DFND",
      "voting_sole": 1059580,
      "voting_shared": 0,
      "voting_none": 0
    },
    {
      "cusip": "22266T109",
      "name_of_issuer": "Coupang Inc",
      "title_of_class": "CL A",
      "shares": 4633124,
      "shares_type": "SH",
      "value": 149187000,
      "put_call": null,
      "investment_discretion": "DFND",
      "voting_sole": 4633124,
      "voting_shared": 0,
      "voting_none": 0
    },
    {
      "cusip": "G25508105",
      "name_of_issuer": "Crh Plc",
      "title_of_class": "ORD",
      "shares": 393820,
      "shares_type": "SH",
      "value": 47219000,
      "put_call": null,
      "investment_discretion": "DFND",
      "voting_sole": 393820,
      "voting_shared": 0,
      "voting_none": 0
    },
    {
      "cusip": "23331A109",
      "name_of_issuer": "D R Horton Inc",
      "title_of_class": "COM",
      "shares": 205150,
      "shares_type": "SH",
      "value": 34767000,
      "put_call": null,
      "investment_discretion": "DFND",
      "voting_sole": 205150,
      "voting_shared": 0,
      "voting_none": 0
    },
    {
      "cusip": "234264109",
      "name_of_issuer": "Daktronics Inc",
      "title_of_class": "COM",
      "shares": 1436936,
      "shares_type": "SH",
      "value": 30061000,
      "put_call": null,
      "investment_discretion": "DFND",
      "voting_sole": 1436936,
      "voting_shared": 0,
      "voting_none": 0
    },
    {
      "cusip": "253393102",
      "name_of_issuer": "Dicks Sporting Goods Inc",
      "title_of_class": "COM",
      "shares": 132425,
      "shares_type": "SH",
      "value": 29427000,
      "put_call": null,
      "investment_discretion": "DFND",
      "voting_sole": 132425,
      "voting_shared": 0,
      "voting_none": 0
    },
    {
      "cusip": "256163106",
      "name_of_issuer": "Docusign Inc",
      "title_of_class": "COM",
      "shares": 1685950,
      "shares_type": "SH",
      "value": 121540000,
      "put_call": null,
      "investment_discretion": "DFND",
      "voting_sole": 1685950,
      "voting_shared": 0,
      "voting_none": 0
    },
    {
      "cusip": "278768106",
      "name_of_issuer": "Echostar Corp",
      "title_of_class": "CL A",
      "shares": 60765,
      "shares_type": "SH",
      "value": 4640000,
      "put_call": null,
      "investment_discretion": "DFND",
      "voting_sole": 60765,
      "voting_shared": 0,
      "voting_none": 0
    },
    {
      "cusip": "29337E102",
      "name_of_issuer": "Enliven Therapeutics Inc",
      "title_of_class": "COM",
      "shares": 947405,
      "shares_type": "SH",
      "value": 19393000,
      "put_call": null,
      "investment_discretion": "DFND",
      "voting_sole": 947405,
      "voting_shared": 0,
      "voting_none": 0
    },
    {
      "cusip": "26884L109",
      "name_of_issuer": "Eqt Corp",
      "title_of_class": "COM",
      "shares": 894950,
      "shares_type": "SH",
      "value": 48712000,
      "put_call": null,
      "investment_discretion": "DFND",
      "voting_sole": 894950,
      "voting_shared": 0,
      "voting_none": 0
    },
    {
      "cusip": "349381103",
      "name_of_issuer": "Figure Technology Solutio",
      "title_of_class": "COM CL A",
      "shares": 2116825,
      "shares_type": "SH",
      "value": 76989000,
      "put_call": null,
      "investment_discretion": "DFND",
      "voting_sole": 2116825,
      "voting_shared": 0,
      "voting_none": 0
    },
    {
      "cusip": "G3643J108",
      "name_of_issuer": "Flutter Entmt Plc",
      "title_of_class": "SHS",
      "shares": 115245,
      "shares_type": "SH",
      "value": 29272000,
      "put_call": null,
      "investment_discretion": "DFND",
      "voting_sole": 115245,
      "voting_shared": 0,
      "voting_none": 0
    },
    {
      "cusip": "36828A101",
      "name_of_issuer": "Ge Vernova Inc",
      "title_of_class": "COM",
      "shares": 77320,
      "shares_type": "SH",
      "value": 47544000,
      "put_call": null,
      "investment_discretion": "DFND",
      "voting_sole": 77320,
      "voting_shared": 0,
      "voting_none": 0
    },
    {
      "cusip": "372460105",
      "name_of_issuer": "Genuine Parts Co",
      "title_of_class": "COM",
      "shares": 144185,
      "shares_type": "SH",
      "value": 19984000,
      "put_call": null,
      "investment_discretion": "DFND",
      "voting_sole": 144185,
      "voting_shared": 0,
      "voting_none": 0
    },
    {
      "cusip": "37950E259",
      "name_of_issuer": "Global X Fds",
      "title_of_class": "GB MSCI AR ETF",
      "shares": 254045,
      "shares_type": "SH",
      "value": 17722000,
      "put_call": null,
      "investment_discretion": "DFND",
      "voting_sole": 254045,
      "voting_shared": 0,
      "voting_none": 0
    },
    {
      "cusip": "457669307",
      "name_of_issuer": "Insmed Inc",
      "title_of_class": "COM PAR $.01",
      "shares": 2423435,
      "shares_type": "SH",
      "value": 348999000,
      "put_call": null,
      "investment_discretion": "DFND",
      "voting_sole": 2423435,
      "voting_shared": 0,
      "voting_none": 0
    },
    {
      "cusip": "464287234",
      "name_of_issuer": "Ishares Tr",
      "title_of_class": "MSCI EMG MKT ETF",
      "shares": 1900000,
      "shares_type": "SH",
      "value": 101460000,
      "put_call": null,
      "investment_discretion": "DFND",
      "voting_sole": 1900000,
      "voting_shared": 0,
      "voting_none": 0
    },
    {
      "cusip": "464287655",
      "name_of_issuer": "Ishares Tr",
      "title_of_class": "RUSSELL 2000 ETF",
      "shares": 226000,
      "shares_type": "SH",
      "value": 54683000,
      "put_call": "Call",
      "investment_discretion": "DFND",
      "voting_sole": 226000,
      "voting_shared": 0,
      "voting_none": 0
    },
    {
      "cusip": "526057104",
      "name_of_issuer": "Lennar Corp",
      "title_of_class": "CL A",
      "shares": 279424,
      "shares_type": "SH",
      "value": 35219000,
      "put_call": null,
      "investment_discretion": "DFND",
      "voting_sole": 279424,
      "voting_shared": 0,
      "voting_none": 0
    },
    {
      "cusip": "531229755",
      "name_of_issuer": "Liberty Media Corp Del",
      "title_of_class": "COM LBTY ONE S C",
      "shares": 288400,
      "shares_type": "SH",
      "value": 30123000,
      "put_call": null,
      "investment_discretion": "DFND",
      "voting_sole": 288400,
      "voting_shared": 0,
      "voting_none": 0
    },
    {
      "cusip": "58733R102",
      "name_of_issuer": "Mercadolibre Inc",
      "title_of_class": "COM",
      "shares": 58344,
      "shares_type": "SH",
      "value": 136346000,
      "put_call": null,
      "investment_discretion": "DFND",
      "voting_sole": 58344,
      "voting_shared": 0,
      "voting_none": 0
    },
    {
      "cusip": "30303M102",
      "name_of_issuer": "Meta Platforms Inc",
      "title_of_class": "CL A",
      "shares": 76100,
      "shares_type": "SH",
      "value": 55886000,
      "put_call": null,
      "investment_discretion": "DFND",
      "voting_sole": 76100,
      "voting_shared": 0,
      "voting_none": 0
    },
    {
      "cusip": "60937P106",
      "name_of_issuer": "Mongodb Inc",
      "title_of_class": "CL A",
      "shares": 17710,
      "shares_type": "SH",
      "value": 5497000,
      "put_call": null,
      "investment_discretion": "DFND",
      "voting_sole": 17710,
      "voting_shared": 0,
      "voting_none": 0
    },
    {
      "cusip": "632307104",
      "name_of_issuer": "Natera Inc",
      "title_of_class": "COM",
      "shares": 3214532,
      "shares_type": "SH",
      "value": 517443000,
      "put_call": null,
      "investment_discretion": "DFND",
      "voting_sole": 3214532,
      "voting_shared": 0,
      "voting_none": 0
    },
    {
      "cusip": "632307104",
      "name_of_issuer": "Natera Inc",
      "title_of_class": "COM",
      "shares": 100000,
      "shares_type": "SH",
      "value": 16097000,
      "put_call": "Call",
      "investment_discretion": "DFND",
      "voting_sole": 100000,
      "voting_shared": 0,
      "voting_none": 0
    },
    {
      "cusip": "N62509109",
      "name_of_issuer": "Newamsterdam Pharma Company",
      "title_of_class": "ORDINARY SHARES",
      "shares": 1923700,
      "shares_type": "SH",
      "value": 54710000,
      "put_call": null,
      "investment_discretion": "DFND",
      "voting_sole": 1923700,
      "voting_shared": 0,
      "voting_none": 0
    },
    {
      "cusip": "G6683N103",
      "name_of_issuer": "Nu Hldgs Ltd",
      "title_of_class": "ORD SHS CL A",
      "shares": 1454180,
      "shares_type": "SH",
      "value": 23281000,
      "put_call": null,
      "investment_discretion": "DFND",
      "voting_sole": 1454180,
      "voting_shared": 0,
      "voting_none": 0
    },
    {
      "cusip": "68404L201",
      "name_of_issuer": "Option Care Health Inc",
      "title_of_class": "COM NEW",
      "shares": 977685,
      "shares_type": "SH",
      "value": 27141000,
      "put_call": null,
      "investment_discretion": "DFND",
      "voting_sole": 977685,
      "voting_shared": 0,
      "voting_none": 0
    },
    {
      "cusip": "69331C108",
      "name_of_issuer": "Pg&E Corp",
      "title_of_class": "COM",
      "shares": 1649300,
      "shares_type": "SH",
      "value": 24871000,
      "put_call": null,
      "investment_discretion": "DFND",
      "voting_sole": 1649300,
      "voting_shared": 0,
      "voting_none": 0
    },
    {
      "cusip": "737446104",
      "name_of_issuer": "Post Hldgs Inc",
      "title_of_class": "COM",
      "shares": 176400,
      "shares_type": "SH",
      "value": 18959000,
      "put_call": null,
      "investment_discretion": "DFND",
      "voting_sole": 176400,
      "voting_shared": 0,
      "voting_none": 0
    },
    {
      "cusip": "74366E102",
      "name_of_issuer": "Protagonist Therapeutics Inc",
      "title_of_class": "COM",
      "shares": 159700,
      "shares_type": "SH",
      "value": 10609000,
      "put_call": null,
      "investment_discretion": "DFND",
      "voting_sole": 159700,
      "voting_shared": 0,
      "voting_none": 0
    },
    {
      "cusip": "74623V103",
      "name_of_issuer": "Purecycle Technologies Inc",
      "title_of_class": "COM",
      "shares": 2303084,
      "shares_type": "SH",
      "value": 30286000,
      "put_call": null,
      "investment_discretion": "DFND",
      "voting_sole": 2303084,
      "voting_shared": 0,
      "voting_none": 0
    },
    {
      "cusip": "76131D103",
      "name_of_issuer": "Restaurant Brands Intl Inc",
      "title_of_class": "COM",
      "shares": 1131365,
      "shares_type": "SH",
      "value": 72566000,
      "put_call": null,
      "investment_discretion": "DFND",
      "voting_sole": 1131365,
      "voting_shared": 0,
      "voting_none": 0
    },
    {
      "cusip": "77543R102",
      "name_of_issuer": "Roku Inc",
      "title_of_class": "COM CL A",
      "shares": 822435,
      "shares_type": "SH",
      "value": 82350000,
      "put_call": null,
      "investment_discretion": "DFND",
      "voting_sole": 822435,
      "voting_shared": 0,
      "voting_none": 0
    },
    {
      "cusip": "80004C200",
      "name_of_issuer": "Sandisk Corp",
      "title_of_class": "COM",
      "shares": 166235,
      "shares_type": "SH",
      "value": 18652000,
      "put_call": null,
      "investment_discretion": "DFND",
      "voting_sole": 166235,
      "voting_shared": 0,
      "voting_none": 0
    },
    {
      "cusip": "81141R100",
      "name_of_issuer": "Sea Ltd",
      "title_of_class": "SPONSORD ADS",
      "shares": 274200,
      "shares_type": "SH",
      "value": 49008000,
      "put_call": null,
      "investment_discretion": "DFND",
      "voting_sole": 274200,
      "voting_shared": 0,
      "voting_none": 0
    },
    {
      "cusip": "G7997R103",
      "name_of_issuer": "Seagate Technology Hldngs Pl",
      "title_of_class": "ORD SHS",
      "shares": 85900,
      "shares_type": "SH",
      "value": 20278000,
      "put_call": null,
      "investment_discretion": "DFND",
      "voting_sole": 85900,
      "voting_shared": 0,
      "voting_none": 0
    },
    {
      "cusip": "816850101",
      "name_of_issuer": "Semtech Corp",
      "title_of_class": "COM",
      "shares": 301515,
      "shares_type": "SH",
      "value": 21543000,
      "put_call": null,
      "investment_discretion": "DFND",
      "voting_sole": 301515,
      "voting_shared": 0,
      "voting_none": 0
    },
    {
      "cusip": "83418M103",
      "name_of_issuer": "Solaris Energy Infras Inc",
      "title_of_class": "COM CL A",
      "shares": 145600,
      "shares_type": "SH",
      "value": 5820000,
      "put_call": null,
      "investment_discretion": "DFND",
      "voting_sole": 145600,
      "voting_shared": 0,
      "voting_none": 0
    },
    {
      "cusip": "78462F103",
      "name_of_issuer": "Spdr S&P 500 Etf Tr",
      "title_of_class": "TR UNIT",
      "shares": 90000,
      "shares_type": "SH",
      "value": 59956000,
      "put_call": "Call",
      "investment_discretion": "DFND",
      "voting_sole": 90000,
      "voting_shared": 0,
      "voting_none": 0
    },
    {
      "cusip": "78464A797",
      "name_of_issuer": "Spdr Series Trust",
      "title_of_class": "S&P BK ETF",
      "shares": 482095,
      "shares_type": "SH",
      "value": 28646000,
      "put_call": null,
      "investment_discretion": "DFND",
      "voting_sole": 482095,
      "voting_shared": 0,
      "voting_none": 0
    },
    {
      "cusip": "86384P109",
      "name_of_issuer": "Stubhub Hldgs Inc",
      "title_of_class": "CL A",
      "shares": 4259516,
      "shares_type": "SH",
      "value": 71730000,
      "put_call": null,
      "investment_discretion": "DFND",
      "voting_sole": 4259516,
      "voting_shared": 0,
      "voting_none": 0
    },
    {
      "cusip": "87165B103",
      "name_of_issuer": "Synchrony Financial",
      "title_of_class": "COM",
      "shares": 261825,
      "shares_type": "SH",
      "value": 18603000,
      "put_call": null,
      "investment_discretion": "DFND",
      "voting_sole": 261825,
      "voting_shared": 0,
      "voting_none": 0
    },
    {
      "cusip": "874039100",
      "name_of_issuer": "Taiwan Semiconductor Mfg Ltd",
      "title_of_class": "SPONSORED ADS",
      "shares": 765085,
      "shares_type": "SH",
      "value": 213681000,
      "put_call": null,
      "investment_discretion": "DFND",
      "voting_sole": 765085,
      "voting_shared": 0,
      "voting_none": 0
    },
    {
      "cusip": "881624209",
      "name_of_issuer": "Teva Pharmaceutical Inds Ltd",
      "title_of_class": "SPONSORED ADS",
      "shares": 16593935,
      "shares_type": "SH",
      "value": 335197000,
      "put_call": null,
      "investment_discretion": "DFND",
      "voting_sole": 16593935,
      "voting_shared": 0,
      "voting_none": 0
    },
    {
      "cusip": "882681109",
      "name_of_issuer": "Texas Roadhouse Inc",
      "title_of_class": "COM",
      "shares": 29800,
      "shares_type": "SH",
      "value": 4951000,
      "put_call": null,
      "investment_discretion": "DFND",
      "voting_sole": 29800,
      "voting_shared": 0,
      "voting_none": 0
    },
    {
      "cusip": "90138F102",
      "name_of_issuer": "Twilio Inc",
      "title_of_class": "CL A",
      "shares": 512800,
      "shares_type": "SH",
      "value": 51326000,
      "put_call": null,
      "investment_discretion": "DFND",
      "voting_sole": 512800,
      "voting_shared": 0,
      "voting_none": 0
    },
    {
      "cusip": "91332U101",
      "name_of_issuer": "Unity Software Inc",
      "title_of_class": "COM",
      "shares": 882500,
      "shares_type": "SH",
      "value": 35335000,
      "put_call": null,
      "investment_discretion": "DFND",
      "voting_sole": 882500,
      "voting_shared": 0,
      "voting_none": 0
    },
    {
      "cusip": "925050106",
      "name_of_issuer": "Verona Pharma Plc",
      "title_of_class": "SPONSORED ADS",
      "shares": 1002080,
      "shares_type": "SH",
      "value": 106932000,
      "put_call": null,
      "investment_discretion": "DFND",
      "voting_sole": 1002080,
      "voting_shared": 0,
      "voting_none": 0
    },
    {
      "cusip": "92840M102",
      "name_of_issuer": "Vistra Corp",
      "title_of_class": "COM",
      "shares": 233985,
      "shares_type": "SH",
      "value": 45842000,
      "put_call": null,
      "investment_discretion": "DFND",
      "voting_sole": 233985,
      "voting_shared": 0,
      "voting_none": 0
    },
    {
      "cusip": "929740108",
      "name_of_issuer": "Wabtec",
      "title_of_class": "COM",
      "shares": 302410,
      "shares_type": "SH",
      "value": 60624000,
      "put_call": null,
      "investment_discretion": "DFND",
      "voting_sole": 302410,
      "voting_shared": 0,
      "voting_none": 0
    },
    {
      "cusip": "980745103",
      "name_of_issuer": "Woodward Inc",
      "title_of_class": "COM",
      "shares": 633015,
      "shares_type": "SH",
      "value": 159969000,
      "put_call": null,
      "investment_discretion": "DFND",
      "voting_sole": 633015,
      "voting_shared": 0,
      "voting_none": 0
    },
    {
      "cusip": "984245100",
      "name_of_issuer": "Ypf Sociedad Anonima",
      "title_of_class": "SPON ADR CL D",
      "shares": 114695,
      "shares_type": "SH",
      "value": 2786000,
      "put_call": null,
      "investment_discretion": "DFND",
      "voting_sole": 114695,
      "voting_shared": 0,
      "voting_none": 0
    }
  ]
}
